[
 {
  "RuleID": "generic-api-key",
  "Description": "Detected a Generic API Key, potentially exposing access to various services and sensitive operations.",
  "StartLine": 10,
  "EndLine": 10,
  "StartColumn": 5,
  "EndColumn": 79,
  "Match": "Secret\": \"eyJ0eXBlIjoic2VydmljZV9hY2NvdW50IiwicHJvamVjdF9pZCI6InRlc3QifQ==\"",
  "Secret": "eyJ0eXBlIjoic2VydmljZV9hY2NvdW50IiwicHJvamVjdF9pZCI6InRlc3QifQ==",
  "File": "gitleaks-baseline.new.json",
  "SymlinkFile": "",
  "Commit": "",
  "Entropy": 5.0347743,
  "Author": "",
  "Email": "",
  "Date": "",
  "Message": "",
  "Tags": [],
  "Fingerprint": "gitleaks-baseline.new.json:generic-api-key:10"
 },
 {
  "RuleID": "generic-api-key",
  "Description": "Detected a Generic API Key, potentially exposing access to various services and sensitive operations.",
  "StartLine": 30,
  "EndLine": 30,
  "StartColumn": 5,
  "EndColumn": 40,
  "Match": "Secret\": \"eyJhbGciOiJSUzI1NiJ9.test\"",
  "Secret": "eyJhbGciOiJSUzI1NiJ9.test",
  "File": "gitleaks-baseline.new.json",
  "SymlinkFile": "",
  "Commit": "",
  "Entropy": 4.103465,
  "Author": "",
  "Email": "",
  "Date": "",
  "Message": "",
  "Tags": [],
  "Fingerprint": "gitleaks-baseline.new.json:generic-api-key:30"
 },
 {
  "RuleID": "generic-api-key",
  "Description": "Detected a Generic API Key, potentially exposing access to various services and sensitive operations.",
  "StartLine": 50,
  "EndLine": 50,
  "StartColumn": 5,
  "EndColumn": 31,
  "Match": "Secret\": \"abc-123_XYZ.test\"",
  "Secret": "abc-123_XYZ.test",
  "File": "gitleaks-baseline.new.json",
  "SymlinkFile": "",
  "Commit": "",
  "Entropy": 3.875,
  "Author": "",
  "Email": "",
  "Date": "",
  "Message": "",
  "Tags": [],
  "Fingerprint": "gitleaks-baseline.new.json:generic-api-key:50"
 },
 {
  "RuleID": "generic-api-key",
  "Description": "Detected a Generic API Key, potentially exposing access to various services and sensitive operations.",
  "StartLine": 70,
  "EndLine": 70,
  "StartColumn": 5,
  "EndColumn": 27,
  "Match": "Secret\": \"shpkey_12345\"",
  "Secret": "shpkey_12345",
  "File": "gitleaks-baseline.new.json",
  "SymlinkFile": "",
  "Commit": "",
  "Entropy": 3.5849626,
  "Author": "",
  "Email": "",
  "Date": "",
  "Message": "",
  "Tags": [],
  "Fingerprint": "gitleaks-baseline.new.json:generic-api-key:70"
 },
 {
  "RuleID": "generic-api-key",
  "Description": "Detected a Generic API Key, potentially exposing access to various services and sensitive operations.",
  "StartLine": 90,
  "EndLine": 90,
  "StartColumn": 5,
  "EndColumn": 27,
  "Match": "Secret\": \"shpkey_12345\"",
  "Secret": "shpkey_12345",
  "File": "gitleaks-baseline.new.json",
  "SymlinkFile": "",
  "Commit": "",
  "Entropy": 3.5849626,
  "Author": "",
  "Email": "",
  "Date": "",
  "Message": "",
  "Tags": [],
  "Fingerprint": "gitleaks-baseline.new.json:generic-api-key:90"
 },
 {
  "RuleID": "generic-api-key",
  "Description": "Detected a Generic API Key, potentially exposing access to various services and sensitive operations.",
  "StartLine": 110,
  "EndLine": 110,
  "StartColumn": 5,
  "EndColumn": 27,
  "Match": "Secret\": \"shpkey_12345\"",
  "Secret": "shpkey_12345",
  "File": "gitleaks-baseline.new.json",
  "SymlinkFile": "",
  "Commit": "",
  "Entropy": 3.5849626,
  "Author": "",
  "Email": "",
  "Date": "",
  "Message": "",
  "Tags": [],
  "Fingerprint": "gitleaks-baseline.new.json:generic-api-key:110"
 },
 {
  "RuleID": "generic-api-key",
  "Description": "Detected a Generic API Key, potentially exposing access to various services and sensitive operations.",
  "StartLine": 130,
  "EndLine": 130,
  "StartColumn": 5,
  "EndColumn": 27,
  "Match": "Secret\": \"shpkey_12345\"",
  "Secret": "shpkey_12345",
  "File": "gitleaks-baseline.new.json",
  "SymlinkFile": "",
  "Commit": "",
  "Entropy": 3.5849626,
  "Author": "",
  "Email": "",
  "Date": "",
  "Message": "",
  "Tags": [],
  "Fingerprint": "gitleaks-baseline.new.json:generic-api-key:130"
 },
 {
  "RuleID": "generic-api-key",
  "Description": "Detected a Generic API Key, potentially exposing access to various services and sensitive operations.",
  "StartLine": 150,
  "EndLine": 150,
  "StartColumn": 5,
  "EndColumn": 27,
  "Match": "Secret\": \"shpkey_12345\"",
  "Secret": "shpkey_12345",
  "File": "gitleaks-baseline.new.json",
  "SymlinkFile": "",
  "Commit": "",
  "Entropy": 3.5849626,
  "Author": "",
  "Email": "",
  "Date": "",
  "Message": "",
  "Tags": [],
  "Fingerprint": "gitleaks-baseline.new.json:generic-api-key:150"
 },
 {
  "RuleID": "generic-api-key",
  "Description": "Detected a Generic API Key, potentially exposing access to various services and sensitive operations.",
  "StartLine": 170,
  "EndLine": 170,
  "StartColumn": 5,
  "EndColumn": 27,
  "Match": "Secret\": \"shpkey_12345\"",
  "Secret": "shpkey_12345",
  "File": "gitleaks-baseline.new.json",
  "SymlinkFile": "",
  "Commit": "",
  "Entropy": 3.5849626,
  "Author": "",
  "Email": "",
  "Date": "",
  "Message": "",
  "Tags": [],
  "Fingerprint": "gitleaks-baseline.new.json:generic-api-key:170"
 },
 {
  "RuleID": "generic-api-key",
  "Description": "Detected a Generic API Key, potentially exposing access to various services and sensitive operations.",
  "StartLine": 190,
  "EndLine": 190,
  "StartColumn": 5,
  "EndColumn": 58,
  "Match": "Secret\": \"LXs5ovMHyr4wSkLSS8XATVtuuyO7wtP9kE.DBZLaCbQ\"",
  "Secret": "LXs5ovMHyr4wSkLSS8XATVtuuyO7wtP9kE.DBZLaCbQ",
  "File": "gitleaks-baseline.new.json",
  "SymlinkFile": "",
  "Commit": "",
  "Entropy": 4.9260373,
  "Author": "",
  "Email": "",
  "Date": "",
  "Message": "",
  "Tags": [],
  "Fingerprint": "gitleaks-baseline.new.json:generic-api-key:190"
 },
 {
  "RuleID": "generic-api-key",
  "Description": "Detected a Generic API Key, potentially exposing access to various services and sensitive operations.",
  "StartLine": 210,
  "EndLine": 210,
  "StartColumn": 5,
  "EndColumn": 58,
  "Match": "Secret\": \"LXs5ovMHyr4wSkLSS8XATVtuuyO7wtP9kE.DBZLaCbQ\"",
  "Secret": "LXs5ovMHyr4wSkLSS8XATVtuuyO7wtP9kE.DBZLaCbQ",
  "File": "gitleaks-baseline.new.json",
  "SymlinkFile": "",
  "Commit": "",
  "Entropy": 4.9260373,
  "Author": "",
  "Email": "",
  "Date": "",
  "Message": "",
  "Tags": [],
  "Fingerprint": "gitleaks-baseline.new.json:generic-api-key:210"
 },
 {
  "RuleID": "generic-api-key",
  "Description": "Detected a Generic API Key, potentially exposing access to various services and sensitive operations.",
  "StartLine": 230,
  "EndLine": 230,
  "StartColumn": 5,
  "EndColumn": 30,
  "Match": "Secret\": \"abc.DEF-123_456\"",
  "Secret": "abc.DEF-123_456",
  "File": "gitleaks-baseline.new.json",
  "SymlinkFile": "",
  "Commit": "",
  "Entropy": 3.9068906,
  "Author": "",
  "Email": "",
  "Date": "",
  "Message": "",
  "Tags": [],
  "Fingerprint": "gitleaks-baseline.new.json:generic-api-key:230"
 },
 {
  "RuleID": "generic-api-key",
  "Description": "Detected a Generic API Key, potentially exposing access to various services and sensitive operations.",
  "StartLine": 250,
  "EndLine": 250,
  "StartColumn": 5,
  "EndColumn": 30,
  "Match": "Secret\": \"abc.DEF-123_456\"",
  "Secret": "abc.DEF-123_456",
  "File": "gitleaks-baseline.new.json",
  "SymlinkFile": "",
  "Commit": "",
  "Entropy": 3.9068906,
  "Author": "",
  "Email": "",
  "Date": "",
  "Message": "",
  "Tags": [],
  "Fingerprint": "gitleaks-baseline.new.json:generic-api-key:250"
 },
 {
  "RuleID": "generic-api-key",
  "Description": "Detected a Generic API Key, potentially exposing access to various services and sensitive operations.",
  "StartLine": 270,
  "EndLine": 270,
  "StartColumn": 5,
  "EndColumn": 40,
  "Match": "Secret\": \"eyJhbGciOiJSUzI1NiJ9.test\"",
  "Secret": "eyJhbGciOiJSUzI1NiJ9.test",
  "File": "gitleaks-baseline.new.json",
  "SymlinkFile": "",
  "Commit": "",
  "Entropy": 4.103465,
  "Author": "",
  "Email": "",
  "Date": "",
  "Message": "",
  "Tags": [],
  "Fingerprint": "gitleaks-baseline.new.json:generic-api-key:270"
 },
 {
  "RuleID": "generic-api-key",
  "Description": "Detected a Generic API Key, potentially exposing access to various services and sensitive operations.",
  "StartLine": 290,
  "EndLine": 290,
  "StartColumn": 5,
  "EndColumn": 31,
  "Match": "Secret\": \"abc-123_XYZ.test\"",
  "Secret": "abc-123_XYZ.test",
  "File": "gitleaks-baseline.new.json",
  "SymlinkFile": "",
  "Commit": "",
  "Entropy": 3.875,
  "Author": "",
  "Email": "",
  "Date": "",
  "Message": "",
  "Tags": [],
  "Fingerprint": "gitleaks-baseline.new.json:generic-api-key:290"
 },
 {
  "RuleID": "generic-api-key",
  "Description": "Detected a Generic API Key, potentially exposing access to various services and sensitive operations.",
  "StartLine": 310,
  "EndLine": 310,
  "StartColumn": 5,
  "EndColumn": 79,
  "Match": "Secret\": \"eyJ0eXBlIjoic2VydmljZV9hY2NvdW50IiwicHJvamVjdF9pZCI6InRlc3QifQ==\"",
  "Secret": "eyJ0eXBlIjoic2VydmljZV9hY2NvdW50IiwicHJvamVjdF9pZCI6InRlc3QifQ==",
  "File": "gitleaks-baseline.new.json",
  "SymlinkFile": "",
  "Commit": "",
  "Entropy": 5.0347743,
  "Author": "",
  "Email": "",
  "Date": "",
  "Message": "",
  "Tags": [],
  "Fingerprint": "gitleaks-baseline.new.json:generic-api-key:310"
 },
 {
  "RuleID": "generic-api-key",
  "Description": "Detected a Generic API Key, potentially exposing access to various services and sensitive operations.",
  "StartLine": 330,
  "EndLine": 330,
  "StartColumn": 5,
  "EndColumn": 58,
  "Match": "Secret\": \"LXs5ovMHyr4wSkLSS8XATVtuuyO7wtP9kE.DBZLaCbQ\"",
  "Secret": "LXs5ovMHyr4wSkLSS8XATVtuuyO7wtP9kE.DBZLaCbQ",
  "File": "gitleaks-baseline.new.json",
  "SymlinkFile": "",
  "Commit": "",
  "Entropy": 4.9260373,
  "Author": "",
  "Email": "",
  "Date": "",
  "Message": "",
  "Tags": [],
  "Fingerprint": "gitleaks-baseline.new.json:generic-api-key:330"
 },
 {
  "RuleID": "generic-api-key",
  "Description": "Detected a Generic API Key, potentially exposing access to various services and sensitive operations.",
  "StartLine": 350,
  "EndLine": 350,
  "StartColumn": 5,
  "EndColumn": 58,
  "Match": "Secret\": \"LXs5ovMHyr4wSkLSS8XATVtuuyO7wtP9kE.DBZLaCbQ\"",
  "Secret": "LXs5ovMHyr4wSkLSS8XATVtuuyO7wtP9kE.DBZLaCbQ",
  "File": "gitleaks-baseline.new.json",
  "SymlinkFile": "",
  "Commit": "",
  "Entropy": 4.9260373,
  "Author": "",
  "Email": "",
  "Date": "",
  "Message": "",
  "Tags": [],
  "Fingerprint": "gitleaks-baseline.new.json:generic-api-key:350"
 },
 {
  "RuleID": "generic-api-key",
  "Description": "Detected a Generic API Key, potentially exposing access to various services and sensitive operations.",
  "StartLine": 370,
  "EndLine": 370,
  "StartColumn": 5,
  "EndColumn": 30,
  "Match": "Secret\": \"abc.DEF-123_456\"",
  "Secret": "abc.DEF-123_456",
  "File": "gitleaks-baseline.new.json",
  "SymlinkFile": "",
  "Commit": "",
  "Entropy": 3.9068906,
  "Author": "",
  "Email": "",
  "Date": "",
  "Message": "",
  "Tags": [],
  "Fingerprint": "gitleaks-baseline.new.json:generic-api-key:370"
 },
 {
  "RuleID": "generic-api-key",
  "Description": "Detected a Generic API Key, potentially exposing access to various services and sensitive operations.",
  "StartLine": 390,
  "EndLine": 390,
  "StartColumn": 5,
  "EndColumn": 30,
  "Match": "Secret\": \"abc.DEF-123_456\"",
  "Secret": "abc.DEF-123_456",
  "File": "gitleaks-baseline.new.json",
  "SymlinkFile": "",
  "Commit": "",
  "Entropy": 3.9068906,
  "Author": "",
  "Email": "",
  "Date": "",
  "Message": "",
  "Tags": [],
  "Fingerprint": "gitleaks-baseline.new.json:generic-api-key:390"
 },
 {
  "RuleID": "generic-api-key",
  "Description": "Detected a Generic API Key, potentially exposing access to various services and sensitive operations.",
  "StartLine": 410,
  "EndLine": 410,
  "StartColumn": 5,
  "EndColumn": 27,
  "Match": "Secret\": \"shpkey_12345\"",
  "Secret": "shpkey_12345",
  "File": "gitleaks-baseline.new.json",
  "SymlinkFile": "",
  "Commit": "",
  "Entropy": 3.5849626,
  "Author": "",
  "Email": "",
  "Date": "",
  "Message": "",
  "Tags": [],
  "Fingerprint": "gitleaks-baseline.new.json:generic-api-key:410"
 },
 {
  "RuleID": "generic-api-key",
  "Description": "Detected a Generic API Key, potentially exposing access to various services and sensitive operations.",
  "StartLine": 430,
  "EndLine": 430,
  "StartColumn": 5,
  "EndColumn": 27,
  "Match": "Secret\": \"shpkey_12345\"",
  "Secret": "shpkey_12345",
  "File": "gitleaks-baseline.new.json",
  "SymlinkFile": "",
  "Commit": "",
  "Entropy": 3.5849626,
  "Author": "",
  "Email": "",
  "Date": "",
  "Message": "",
  "Tags": [],
  "Fingerprint": "gitleaks-baseline.new.json:generic-api-key:430"
 },
 {
  "RuleID": "generic-api-key",
  "Description": "Detected a Generic API Key, potentially exposing access to various services and sensitive operations.",
  "StartLine": 450,
  "EndLine": 450,
  "StartColumn": 5,
  "EndColumn": 27,
  "Match": "Secret\": \"shpkey_12345\"",
  "Secret": "shpkey_12345",
  "File": "gitleaks-baseline.new.json",
  "SymlinkFile": "",
  "Commit": "",
  "Entropy": 3.5849626,
  "Author": "",
  "Email": "",
  "Date": "",
  "Message": "",
  "Tags": [],
  "Fingerprint": "gitleaks-baseline.new.json:generic-api-key:450"
 },
 {
  "RuleID": "generic-api-key",
  "Description": "Detected a Generic API Key, potentially exposing access to various services and sensitive operations.",
  "StartLine": 470,
  "EndLine": 470,
  "StartColumn": 5,
  "EndColumn": 27,
  "Match": "Secret\": \"shpkey_12345\"",
  "Secret": "shpkey_12345",
  "File": "gitleaks-baseline.new.json",
  "SymlinkFile": "",
  "Commit": "",
  "Entropy": 3.5849626,
  "Author": "",
  "Email": "",
  "Date": "",
  "Message": "",
  "Tags": [],
  "Fingerprint": "gitleaks-baseline.new.json:generic-api-key:470"
 },
 {
  "RuleID": "generic-api-key",
  "Description": "Detected a Generic API Key, potentially exposing access to various services and sensitive operations.",
  "StartLine": 490,
  "EndLine": 490,
  "StartColumn": 5,
  "EndColumn": 27,
  "Match": "Secret\": \"shpkey_12345\"",
  "Secret": "shpkey_12345",
  "File": "gitleaks-baseline.new.json",
  "SymlinkFile": "",
  "Commit": "",
  "Entropy": 3.5849626,
  "Author": "",
  "Email": "",
  "Date": "",
  "Message": "",
  "Tags": [],
  "Fingerprint": "gitleaks-baseline.new.json:generic-api-key:490"
 },
 {
  "RuleID": "generic-api-key",
  "Description": "Detected a Generic API Key, potentially exposing access to various services and sensitive operations.",
  "StartLine": 510,
  "EndLine": 510,
  "StartColumn": 5,
  "EndColumn": 27,
  "Match": "Secret\": \"shpkey_12345\"",
  "Secret": "shpkey_12345",
  "File": "gitleaks-baseline.new.json",
  "SymlinkFile": "",
  "Commit": "",
  "Entropy": 3.5849626,
  "Author": "",
  "Email": "",
  "Date": "",
  "Message": "",
  "Tags": [],
  "Fingerprint": "gitleaks-baseline.new.json:generic-api-key:510"
 },
 {
  "RuleID": "generic-api-key",
  "Description": "Detected a Generic API Key, potentially exposing access to various services and sensitive operations.",
  "StartLine": 162,
  "EndLine": 162,
  "StartColumn": 46,
  "EndColumn": 129,
  "Match": "credentials_base64=eyJ0eXBlIjoic2VydmljZV9hY2NvdW50IiwicHJvamVjdF9pZCI6InRlc3QifQ==\"",
  "Secret": "eyJ0eXBlIjoic2VydmljZV9hY2NvdW50IiwicHJvamVjdF9pZCI6InRlc3QifQ==",
  "File": "pkg/destination/bigquery/bigquery_test.go",
  "SymlinkFile": "",
  "Commit": "",
  "Entropy": 5.0347743,
  "Author": "",
  "Email": "",
  "Date": "",
  "Message": "",
  "Tags": [],
  "Fingerprint": "pkg/destination/bigquery/bigquery_test.go:generic-api-key:162"
 },
 {
  "RuleID": "generic-api-key",
  "Description": "Detected a Generic API Key, potentially exposing access to various services and sensitive operations.",
  "StartLine": 51,
  "EndLine": 51,
  "StartColumn": 24,
  "EndColumn": 57,
  "Match": "api_key=eyJhbGciOiJSUzI1NiJ9.test\"",
  "Secret": "eyJhbGciOiJSUzI1NiJ9.test",
  "File": "pkg/source/hostaway/hostaway_test.go",
  "SymlinkFile": "",
  "Commit": "",
  "Entropy": 4.103465,
  "Author": "",
  "Email": "",
  "Date": "",
  "Message": "",
  "Tags": [],
  "Fingerprint": "pkg/source/hostaway/hostaway_test.go:generic-api-key:51"
 },
 {
  "RuleID": "generic-api-key",
  "Description": "Detected a Generic API Key, potentially exposing access to various services and sensitive operations.",
  "StartLine": 21,
  "EndLine": 21,
  "StartColumn": 26,
  "EndColumn": 48,
  "Match": "token=abc-123_XYZ.test\"",
  "Secret": "abc-123_XYZ.test",
  "File": "pkg/source/isoc_pulse/isoc_pulse_test.go",
  "SymlinkFile": "",
  "Commit": "",
  "Entropy": 3.875,
  "Author": "",
  "Email": "",
  "Date": "",
  "Message": "",
  "Tags": [],
  "Fingerprint": "pkg/source/isoc_pulse/isoc_pulse_test.go:generic-api-key:21"
 },
 {
  "RuleID": "generic-api-key",
  "Description": "Detected a Generic API Key, potentially exposing access to various services and sensitive operations.",
  "StartLine": 24,
  "EndLine": 24,
  "StartColumn": 33,
  "EndColumn": 89,
  "Match": "access_token=LXs5ovMHyr4wSkLSS8XATVtuuyO7wtP9kE.DBZLaCbQ\"",
  "Secret": "LXs5ovMHyr4wSkLSS8XATVtuuyO7wtP9kE.DBZLaCbQ",
  "File": "pkg/source/surveymonkey/surveymonkey_test.go",
  "SymlinkFile": "",
  "Commit": "",
  "Entropy": 4.9260373,
  "Author": "",
  "Email": "",
  "Date": "",
  "Message": "",
  "Tags": [],
  "Fingerprint": "pkg/source/surveymonkey/surveymonkey_test.go:generic-api-key:24"
 },
 {
  "RuleID": "generic-api-key",
  "Description": "Detected a Generic API Key, potentially exposing access to various services and sensitive operations.",
  "StartLine": 25,
  "EndLine": 25,
  "StartColumn": 5,
  "EndColumn": 60,
  "Match": "wantToken: \"LXs5ovMHyr4wSkLSS8XATVtuuyO7wtP9kE.DBZLaCbQ\"",
  "Secret": "LXs5ovMHyr4wSkLSS8XATVtuuyO7wtP9kE.DBZLaCbQ",
  "File": "pkg/source/surveymonkey/surveymonkey_test.go",
  "SymlinkFile": "",
  "Commit": "",
  "Entropy": 4.9260373,
  "Author": "",
  "Email": "",
  "Date": "",
  "Message": "",
  "Tags": [],
  "Fingerprint": "pkg/source/surveymonkey/surveymonkey_test.go:generic-api-key:25"
 },
 {
  "RuleID": "generic-api-key",
  "Description": "Detected a Generic API Key, potentially exposing access to various services and sensitive operations.",
  "StartLine": 53,
  "EndLine": 53,
  "StartColumn": 33,
  "EndColumn": 61,
  "Match": "access_token=abc.DEF-123_456\"",
  "Secret": "abc.DEF-123_456",
  "File": "pkg/source/surveymonkey/surveymonkey_test.go",
  "SymlinkFile": "",
  "Commit": "",
  "Entropy": 3.9068906,
  "Author": "",
  "Email": "",
  "Date": "",
  "Message": "",
  "Tags": [],
  "Fingerprint": "pkg/source/surveymonkey/surveymonkey_test.go:generic-api-key:53"
 },
 {
  "RuleID": "generic-api-key",
  "Description": "Detected a Generic API Key, potentially exposing access to various services and sensitive operations.",
  "StartLine": 54,
  "EndLine": 54,
  "StartColumn": 5,
  "EndColumn": 32,
  "Match": "wantToken: \"abc.DEF-123_456\"",
  "Secret": "abc.DEF-123_456",
  "File": "pkg/source/surveymonkey/surveymonkey_test.go",
  "SymlinkFile": "",
  "Commit": "",
  "Entropy": 3.9068906,
  "Author": "",
  "Email": "",
  "Date": "",
  "Message": "",
  "Tags": [],
  "Fingerprint": "pkg/source/surveymonkey/surveymonkey_test.go:generic-api-key:54"
 },
 {
  "RuleID": "generic-api-key",
  "Description": "Detected a Generic API Key, potentially exposing access to various services and sensitive operations.",
  "StartLine": 33,
  "EndLine": 33,
  "StartColumn": 50,
  "EndColumn": 70,
  "Match": "api_key=shpkey_12345\"",
  "Secret": "shpkey_12345",
  "File": "pkg/source/shopify/shopify_test.go",
  "SymlinkFile": "",
  "Commit": "",
  "Entropy": 3.5849626,
  "Author": "",
  "Email": "",
  "Date": "",
  "Message": "",
  "Tags": [],
  "Fingerprint": "pkg/source/shopify/shopify_test.go:generic-api-key:33"
 },
 {
  "RuleID": "generic-api-key",
  "Description": "Detected a Generic API Key, potentially exposing access to various services and sensitive operations.",
  "StartLine": 35,
  "EndLine": 35,
  "StartColumn": 5,
  "EndColumn": 29,
  "Match": "wantKey:   \"shpkey_12345\"",
  "Secret": "shpkey_12345",
  "File": "pkg/source/shopify/shopify_test.go",
  "SymlinkFile": "",
  "Commit": "",
  "Entropy": 3.5849626,
  "Author": "",
  "Email": "",
  "Date": "",
  "Message": "",
  "Tags": [],
  "Fingerprint": "pkg/source/shopify/shopify_test.go:generic-api-key:35"
 },
 {
  "RuleID": "generic-api-key",
  "Description": "Detected a Generic API Key, potentially exposing access to various services and sensitive operations.",
  "StartLine": 40,
  "EndLine": 40,
  "StartColumn": 36,
  "EndColumn": 56,
  "Match": "api_key=shpkey_12345\"",
  "Secret": "shpkey_12345",
  "File": "pkg/source/shopify/shopify_test.go",
  "SymlinkFile": "",
  "Commit": "",
  "Entropy": 3.5849626,
  "Author": "",
  "Email": "",
  "Date": "",
  "Message": "",
  "Tags": [],
  "Fingerprint": "pkg/source/shopify/shopify_test.go:generic-api-key:40"
 },
 {
  "RuleID": "generic-api-key",
  "Description": "Detected a Generic API Key, potentially exposing access to various services and sensitive operations.",
  "StartLine": 42,
  "EndLine": 42,
  "StartColumn": 5,
  "EndColumn": 29,
  "Match": "wantKey:   \"shpkey_12345\"",
  "Secret": "shpkey_12345",
  "File": "pkg/source/shopify/shopify_test.go",
  "SymlinkFile": "",
  "Commit": "",
  "Entropy": 3.5849626,
  "Author": "",
  "Email": "",
  "Date": "",
  "Message": "",
  "Tags": [],
  "Fingerprint": "pkg/source/shopify/shopify_test.go:generic-api-key:42"
 },
 {
  "RuleID": "generic-api-key",
  "Description": "Detected a Generic API Key, potentially exposing access to various services and sensitive operations.",
  "StartLine": 75,
  "EndLine": 75,
  "StartColumn": 26,
  "EndColumn": 46,
  "Match": "api_key=shpkey_12345\"",
  "Secret": "shpkey_12345",
  "File": "pkg/source/shopify/shopify_test.go",
  "SymlinkFile": "",
  "Commit": "",
  "Entropy": 3.5849626,
  "Author": "",
  "Email": "",
  "Date": "",
  "Message": "",
  "Tags": [],
  "Fingerprint": "pkg/source/shopify/shopify_test.go:generic-api-key:75"
 },
 {
  "RuleID": "generic-api-key",
  "Description": "Detected a Generic API Key, potentially exposing access to various services and sensitive operations.",
  "StartLine": 80,
  "EndLine": 80,
  "StartColumn": 35,
  "EndColumn": 55,
  "Match": "api_key=shpkey_12345\"",
  "Secret": "shpkey_12345",
  "File": "pkg/source/shopify/shopify_test.go",
  "SymlinkFile": "",
  "Commit": "",
  "Entropy": 3.5849626,
  "Author": "",
  "Email": "",
  "Date": "",
  "Message": "",
  "Tags": [],
  "Fingerprint": "pkg/source/shopify/shopify_test.go:generic-api-key:80"
 }
]
